{
  "contracts": {
    "DaoSmartContract": {
      "address": "0xaB6aC16f1dD4AaF33Aab2CAe6b9c031DeE51502e",
      "constructorCode": "608060405234801561001057600080fd5b50613a66806100206000396000f3fe",
      "bodyBytecodeHash": "7f09508118a69b47cdc1a4a303412264b98842e730e2022a3decf6d39d5bdfb6",
      "localBytecodeHash": "345d37ee3dbb0e1963d806cfc0cc97bf3d9070456a529506b917a088f6217447",
      "deployedBytecodeHash": "345d37ee3dbb0e1963d806cfc0cc97bf3d9070456a529506b917a088f6217447",
      "types": {
        "t_bool": {
          "id": "t_bool",
          "kind": "elementary",
          "label": "bool"
        },
        "t_uint256": {
          "id": "t_uint256",
          "kind": "elementary",
          "label": "uint256"
        },
        "t_array:50<t_uint256>": {
          "id": "t_array:50<t_uint256>",
          "valueType": "t_uint256",
          "length": "50",
          "kind": "array",
          "label": "uint256[50]"
        },
        "t_address": {
          "id": "t_address",
          "kind": "elementary",
          "label": "address"
        },
        "t_array:49<t_uint256>": {
          "id": "t_array:49<t_uint256>",
          "valueType": "t_uint256",
          "length": "49",
          "kind": "array",
          "label": "uint256[49]"
        },
        "t_mapping<t_bool>": {
          "id": "t_mapping<t_bool>",
          "valueType": "t_bool",
          "label": "mapping(key => bool)",
          "kind": "mapping"
        },
        "t_struct<IDaoSmartContract.Proposal>": {
          "id": "t_struct<IDaoSmartContract.Proposal>",
          "kind": "struct",
          "label": "IDaoSmartContract.Proposal",
          "members": [
            {
              "label": "fundsRequested",
              "astId": 2248,
              "type": "t_uint256",
              "src": "159:22:8"
            },
            {
              "label": "initiationTimestamp",
              "astId": 2250,
              "type": "t_uint256",
              "src": "191:27:8"
            },
            {
              "label": "completionTimestamp",
              "astId": 2252,
              "type": "t_uint256",
              "src": "228:27:8"
            },
            {
              "label": "colletralAmount",
              "astId": 2254,
              "type": "t_uint256",
              "src": "265:23:8"
            },
            {
              "label": "totalMilestones",
              "astId": 2256,
              "type": "t_uint256",
              "src": "298:23:8"
            },
            {
              "label": "completedMilestones",
              "astId": 2258,
              "type": "t_uint256",
              "src": "331:27:8"
            },
            {
              "label": "status",
              "astId": 2260,
              "type": "t_uint256",
              "src": "368:14:8"
            },
            {
              "label": "totalVotes",
              "astId": 2262,
              "type": "t_uint256",
              "src": "392:18:8"
            },
            {
              "label": "proposer",
              "astId": 2264,
              "type": "t_address",
              "src": "420:16:8"
            },
            {
              "label": "isClaimed",
              "astId": 2266,
              "type": "t_bool",
              "src": "446:14:8"
            }
          ]
        },
        "t_mapping<t_struct<IDaoSmartContract.Proposal>>": {
          "id": "t_mapping<t_struct<IDaoSmartContract.Proposal>>",
          "valueType": "t_struct<IDaoSmartContract.Proposal>",
          "label": "mapping(key => IDaoSmartContract.Proposal)",
          "kind": "mapping"
        }
      },
      "storage": [
        {
          "contract": "Initializable",
          "path": "@openzeppelin/contracts-ethereum-package/contracts/Initializable.sol",
          "label": "initialized",
          "astId": 50,
          "type": "t_bool",
          "src": "757:24:1"
        },
        {
          "contract": "Initializable",
          "path": "@openzeppelin/contracts-ethereum-package/contracts/Initializable.sol",
          "label": "initializing",
          "astId": 53,
          "type": "t_bool",
          "src": "876:25:1"
        },
        {
          "contract": "Initializable",
          "path": "@openzeppelin/contracts-ethereum-package/contracts/Initializable.sol",
          "label": "______gap",
          "astId": 118,
          "type": "t_array:50<t_uint256>",
          "src": "1982:29:1"
        },
        {
          "contract": "ContextUpgradeSafe",
          "path": "@openzeppelin/contracts-ethereum-package/contracts/GSN/Context.sol",
          "label": "__gap",
          "astId": 43,
          "type": "t_array:50<t_uint256>",
          "src": "1277:25:0"
        },
        {
          "contract": "OwnableUpgradeSafe",
          "path": "@openzeppelin/contracts-ethereum-package/contracts/access/Ownable.sol",
          "label": "_owner",
          "astId": 132,
          "type": "t_address",
          "src": "700:22:2"
        },
        {
          "contract": "OwnableUpgradeSafe",
          "path": "@openzeppelin/contracts-ethereum-package/contracts/access/Ownable.sol",
          "label": "__gap",
          "astId": 262,
          "type": "t_array:49<t_uint256>",
          "src": "2708:25:2"
        },
        {
          "contract": "MulitpleOwners",
          "path": "contracts/utils/MultipleOwners.sol",
          "label": "isOwner",
          "astId": 2486,
          "type": "t_mapping<t_bool>",
          "src": "161:39:10"
        },
        {
          "contract": "PausableUpgradeSafe",
          "path": "@openzeppelin/contracts-ethereum-package/contracts/utils/Pausable.sol",
          "label": "_paused",
          "astId": 558,
          "type": "t_bool",
          "src": "825:20:5"
        },
        {
          "contract": "PausableUpgradeSafe",
          "path": "@openzeppelin/contracts-ethereum-package/contracts/utils/Pausable.sol",
          "label": "__gap",
          "astId": 647,
          "type": "t_array:49<t_uint256>",
          "src": "2073:25:5"
        },
        {
          "contract": "DaoSmartContract",
          "path": "contracts/DaoSmartContract.sol",
          "label": "daoStakeContract",
          "astId": 668,
          "type": "t_address",
          "src": "575:41:6"
        },
        {
          "contract": "DaoSmartContract",
          "path": "contracts/DaoSmartContract.sol",
          "label": "phnxContract",
          "astId": 670,
          "type": "t_address",
          "src": "622:26:6"
        },
        {
          "contract": "DaoSmartContract",
          "path": "contracts/DaoSmartContract.sol",
          "label": "phnxContractAddress",
          "astId": 672,
          "type": "t_address",
          "src": "655:34:6"
        },
        {
          "contract": "DaoSmartContract",
          "path": "contracts/DaoSmartContract.sol",
          "label": "signer",
          "astId": 674,
          "type": "t_address",
          "src": "696:21:6"
        },
        {
          "contract": "DaoSmartContract",
          "path": "contracts/DaoSmartContract.sol",
          "label": "collateralAmount",
          "astId": 676,
          "type": "t_uint256",
          "src": "724:31:6"
        },
        {
          "contract": "DaoSmartContract",
          "path": "contracts/DaoSmartContract.sol",
          "label": "proposalList",
          "astId": 680,
          "type": "t_mapping<t_struct<IDaoSmartContract.Proposal>>",
          "src": "762:47:6"
        }
      ],
      "warnings": {
        "hasConstructor": false,
        "hasSelfDestruct": false,
        "hasDelegateCall": false,
        "hasInitialValuesInDeclarations": false,
        "uninitializedBaseContracts": []
      }
    }
  },
  "solidityLibs": {},
  "proxies": {
    "dao-smart-contract/DaoSmartContract": [
      {
        "address": "0xfa3Ce6Dd9b0E1C725fc0e91A556191f31E38De9D",
        "version": "1.0.0",
        "implementation": "0xaB6aC16f1dD4AaF33Aab2CAe6b9c031DeE51502e",
        "admin": "0x66DC452c3a7118a3978f0c2D6b9c3889Cc055a37",
        "kind": "Upgradeable"
      }
    ]
  },
  "manifestVersion": "2.2",
  "version": "1.0.0",
  "proxyAdmin": {
    "address": "0x66DC452c3a7118a3978f0c2D6b9c3889Cc055a37"
  }
}
